{"period":{"from":"2026-06-09","to":"2026-07-01","days":22},"network":[{"d":"2026-06-09","total":169,"live":144,"rated":157,"reviews":7166,"avg_rating":4.956},{"d":"2026-07-01","total":169,"live":149,"rated":156,"reviews":7101,"avg_rating":4.931}],"locations":{"Alamo Heights, TX":{"dr":27,"vel":36.8},"Alamo Ranch, TX":{"dr":7,"vel":9.5},"Ashburn, VA":{"dr":7,"vel":9.5},"Ballwin, MO":{"dr":2,"vel":2.7},"Bearden, TN":{"dr":1,"vel":1.4},"Bloomington, MN":{"dr":1,"vel":1.4},"Bonney Lake, WA":{"dr":2,"vel":2.7},"Bountiful, UT":{"dr":7,"vel":9.5},"Broadway Park, CO":{"dr":3,"vel":4.1},"Buckhead, Atlanta, GA":{"dr":2,"vel":2.7},"Bull Creek Market, Austin, TX":{"dr":1,"vel":1.4},"Capitol View, TN":{"dr":2,"vel":2.7},"Cary, NC":{"dr":1,"vel":1.4},"Cedar Hills Crossing, Beaverton, OR":{"dr":2,"vel":2.7,"drat":0.2},"Cedar Park, TX":{"dr":1,"vel":1.4},"Chastain, GA":{"dr":-1,"vel":-1.4},"Claymont, MO":{"dr":4,"vel":5.5},"Colleyville, TX":{"dr":1,"vel":1.4},"Colorado Springs, CO":{"dr":2,"vel":2.7,"went_live":true},"Concord, CA":{"dr":10,"vel":13.6},"Cross Timbers, Flower Mound, TX":{"dr":-1,"vel":-1.4},"Daybreak, UT":{"dr":1,"vel":1.4},"Des Peres, MO":{"dr":1,"vel":1.4},"East Boca, FL":{"dr":6,"vel":8.2},"East Bradenton, FL":{"dr":3,"vel":4.1},"East Brunswick, NJ":{"lost_listing":true},"East Pasadena, CA":{"dr":1,"vel":1.4},"Encinitas, CA":{"dr":1,"vel":1.4},"Fairlawn, OH":{"dr":-1,"vel":-1.4},"Greenville, SC":{"dr":1,"vel":1.4},"Hamilton Mill, Dacula, GA":{"dr":7,"vel":9.5},"Irvine, CA":{"dr":1,"vel":1.4},"Johns Creek, GA":{"dr":-1,"vel":-1.4},"La Jolla, CA":{"went_live":true},"Lincolnshire, IL":{"dr":1,"vel":1.4},"Livingston, NJ":{"dr":4,"vel":5.5},"Mt. Juliet, TN":{"dr":3,"vel":4.1},"Naperville, IL":{"dr":4,"vel":5.5},"North Mansfield, TX":{"dr":2,"vel":2.7},"NorthPointe, Ankeny, IA":{"dr":-6,"vel":-8.2},"O\u2019Fallon, MO":{"dr":1,"vel":1.4,"went_live":true},"Oak Forest, Houston, TX":{"dr":10,"vel":13.6,"drat":-0.2},"Oak Hill, Austin, TX":{"dr":30,"vel":40.9},"Old Town, Alexandria, VA":{"dr":-1,"vel":-1.4},"Orinda, CA":{"dr":-16,"vel":-21.8},"Overland Park, KS":{"dr":1,"vel":1.4},"Paradise Valley, Phoenix, AZ":{"dr":6,"vel":8.2},"Parkway Centre, NC":{"dr":1,"vel":1.4},"Pine Township, Wexford, PA":{"dr":2,"vel":2.7},"Pinecrest, FL":{"dr":6,"vel":8.2},"Reston, VA":{"dr":2,"vel":2.7},"Riverside, CA":{"dr":1,"vel":1.4},"Rochester, MI":{"dr":1,"vel":1.4},"Rochester, NY":{"dr":8,"vel":10.9},"Saddle River, NJ":{"dr":1,"vel":1.4},"Sandy Springs, GA":{"dr":-1,"vel":-1.4},"Schaumburg, IL":{"dr":1,"vel":1.4},"Scottsdale Grayhawk, AZ":{"dr":3,"vel":4.1},"Sienna, TX":{"dr":1,"vel":1.4},"SLP/ St. Louis Park, MN":{"dr":5,"vel":6.8},"South Tampa, FL":{"dr":-1,"vel":-1.4},"South Tempe, AZ":{"dr":2,"vel":2.7},"Southlake, TX":{"dr":3,"vel":4.1},"Spring Creek, OK":{"dr":1,"vel":1.4},"Stonebrook Circle, Frisco, TX":{"dr":-65,"vel":-88.6,"drat":-3.9},"Strongsville, OH":{"dr":1,"vel":1.4},"Sylvania, OH":{"lost_listing":true},"Tanque Verde, Tucson, AZ":{"dr":1,"vel":1.4},"Tega Cay, Fort Mill, SC":{"dr":1,"vel":1.4},"Twenty Mile Road, CO":{"dr":1,"vel":1.4},"Vista Village, CA":{"dr":-1,"vel":-1.4,"went_live":true},"West Arvada, CO":{"dr":7,"vel":9.5},"Westchase, Tampa, FL":{"lost_listing":true},"Westport, Norwalk, CT":{"dr":9,"vel":12.3},"Wildwood, MO":{"dr":1,"vel":1.4},"Woodinville, WA":{"dr":7,"vel":9.5,"went_live":true},"Alloy Eastside | Greenville, SC":{"dr":1,"vel":1.4}}}